gopybuf/__init__.py
gopybuf/server.py
gopybuf/stream.py
gopybuf-0.0.6.dist-info/METADATA
gopybuf-0.0.6.dist-info/WHEEL
gopybuf-0.0.6.dist-info/RECORD
